{"cameraMode":{"drawMode":0,"name":"Shaded","section":"Shading Mode"},"sceneLighting":false,"audioPlay":false,"sceneViewState":{"m_AlwaysRefresh":false,"showFog":true,"showSkybox":false,"showFlares":true,"showImageEffects":true,"showParticleSystems":true,"showVisualEffectGraphs":true,"m_FxEnabled":true},"in2DMode":false,"pivot":{"x":0.0,"y":1.152999997138977,"z":-19.709999084472658},"rotation":{"x":0.10566455125808716,"y":-0.6695887446403503,"z":0.09710311144590378,"w":0.7287690043449402},"size":0.5049751400947571,"orthographic":false}